plain/admin/CHANGELOG.md
plain/admin/README.md
plain/admin/__init__.py
plain/admin/builtin_views.py
plain/admin/config.py
plain/admin/dates.py
plain/admin/middleware.py
plain/admin/models.py
plain/admin/templates.py
plain/admin/toolbar.py
plain/admin/urls.py
plain/admin/utils.py
plain/admin/assets/admin/admin.css
plain/admin/assets/admin/admin.js
plain/admin/assets/admin/bootstrap-icons.svg
plain/admin/assets/admin/charts.js
plain/admin/assets/admin/list.js
plain/admin/assets/admin/menu.js
plain/admin/assets/admin/vendor/chart.js
plain/admin/assets/admin/vendor/jquery-3.7.1.min.js
plain/admin/assets/admin/vendor/popper.min.js
plain/admin/assets/admin/vendor/tippy.css
plain/admin/assets/admin/vendor/tippy.umd.min.js
plain/admin/cards/__init__.py
plain/admin/cards/base.py
plain/admin/cards/charts.py
plain/admin/cards/tables.py
plain/admin/impersonate/__init__.py
plain/admin/impersonate/constants.py
plain/admin/impersonate/middleware.py
plain/admin/impersonate/permissions.py
plain/admin/impersonate/requests.py
plain/admin/impersonate/settings.py
plain/admin/impersonate/urls.py
plain/admin/impersonate/views.py
plain/admin/migrations/0001_initial.py
plain/admin/migrations/__init__.py
plain/admin/templates/admin/_header.html
plain/admin/templates/admin/_menu_section.html
plain/admin/templates/admin/base.html
plain/admin/templates/admin/delete.html
plain/admin/templates/admin/detail.html
plain/admin/templates/admin/index.html
plain/admin/templates/admin/list.html
plain/admin/templates/admin/page.html
plain/admin/templates/admin/search.html
plain/admin/templates/admin/style.html
plain/admin/templates/admin/cards/base.html
plain/admin/templates/admin/cards/card.html
plain/admin/templates/admin/cards/chart.html
plain/admin/templates/admin/cards/table.html
plain/admin/templates/admin/toolbar/button.html
plain/admin/templates/admin/values/UUID.html
plain/admin/templates/admin/values/avatar.html
plain/admin/templates/admin/values/bool.html
plain_admin-0.65.1.dist-info/METADATA
plain_admin-0.65.1.dist-info/WHEEL
plain_admin-0.65.1.dist-info/licenses/LICENSE
plain_admin-0.65.1.dist-info/RECORD
