Metadata-Version: 2.4
Name: plain.admin
Version: 0.65.1
Summary: Manage your app with a backend interface.
Author-email: Dave Gaeddert <dave.gaeddert@dropseed.dev>
License-Expression: BSD-3-Clause
License-File: LICENSE
Requires-Python: >=3.13
Requires-Dist: plain-auth<1.0.0
Requires-Dist: plain-htmx<1.0.0
Requires-Dist: plain-tailwind<1.0.0
Requires-Dist: plain<1.0.0
